zkpwgen.py
zkpwgen-1.0.dist-info/LICENSE
zkpwgen-1.0.dist-info/METADATA
zkpwgen-1.0.dist-info/WHEEL
zkpwgen-1.0.dist-info/entry_points.txt
zkpwgen-1.0.dist-info/top_level.txt
zkpwgen-1.0.dist-info/RECORD
