Metadata-Version: 2.1
Name: zkpwgen
Version: 1.0
Summary: Generate random passwords of full-width Japanese characters
Home-page: https://github.com/amake/zkpwgen
Author: Aaron Madlon-Kay
Author-email: aaron@madlon-kay.com
Keywords: password generator full-width japanese
Classifier: Development Status :: 3 - Alpha
Classifier: Intended Audience :: End Users/Desktop
Classifier: Topic :: Security
Classifier: License :: OSI Approved :: GNU General Public License v2 (GPLv2)
Classifier: Programming Language :: Python :: 2.7
Classifier: Programming Language :: Python :: 3.7
License-File: LICENSE
